openai_vision_cost/__init__.py
openai_vision_cost/calculator.py
openai_vision_cost/exceptions.py
openai_vision_cost/models.py
openai_vision_cost-1.0.0.dist-info/METADATA
openai_vision_cost-1.0.0.dist-info/WHEEL
openai_vision_cost-1.0.0.dist-info/licenses/LICENSE
openai_vision_cost-1.0.0.dist-info/RECORD
