Metadata-Version: 2.4
Name: openai-vision-cost
Version: 1.0.0
Summary: Calculate costs for OpenAI vision model image inputs
Project-URL: Homepage, https://github.com/alexferrari88/openai-vision-cost-calculator
Project-URL: Repository, https://github.com/alexferrari88/openai-vision-cost-calculator
Project-URL: Issues, https://github.com/alexferrari88/openai-vision-cost-calculator/issues
Author-email: Alex Ferrari <alex@thealexferrari.com>
License: MIT License
License-File: LICENSE
Keywords: ai,calculator,cost,openai,tokens,vision
Classifier: Development Status :: 4 - Beta
Classifier: Intended Audience :: Developers
Classifier: License :: OSI Approved :: MIT License
Classifier: Operating System :: OS Independent
Classifier: Programming Language :: Python :: 3
Classifier: Programming Language :: Python :: 3.8
Classifier: Programming Language :: Python :: 3.9
Classifier: Programming Language :: Python :: 3.10
Classifier: Programming Language :: Python :: 3.11
Classifier: Programming Language :: Python :: 3.12
Classifier: Topic :: Scientific/Engineering :: Artificial Intelligence
Classifier: Topic :: Software Development :: Libraries :: Python Modules
Requires-Python: >=3.8
Provides-Extra: dev
Requires-Dist: black>=23.0.0; extra == 'dev'
Requires-Dist: flake8>=6.0.0; extra == 'dev'
Requires-Dist: isort>=5.12.0; extra == 'dev'
Requires-Dist: mypy>=1.0.0; extra == 'dev'
Requires-Dist: pytest-cov>=4.0.0; extra == 'dev'
Requires-Dist: pytest>=7.0.0; extra == 'dev'
